{
	"format_version": "1.16.100",
	"minecraft:item": {
		"description": {
			"identifier": "lc:dt_scp1025",
			"category": "Items"
		},
		"components": {
			"minecraft:use_duration": 2.6,
			"minecraft:creative_category": {
				"parent": "itemGroup.name.items"
			},
			"minecraft:hand_equipped": true,
			"minecraft:max_stack_size": 1,
			"minecraft:icon": {
				"texture": "dt_scp1025"
			},
			"minecraft:display_name": {
				"value": "SCP-1025 \"Encyclopedia of Diseases\""
			},
			"minecraft:cooldown": {
				"duration": 1.8,
				"category": "read"
			},
			"minecraft:on_use": {
				"on_use": {
					"event": "scp1025:read"
				}
			}
		},
		"events": {
			"scp1025:read": {
				"randomize": [
					{
						"weight": 16,
						"add_mob_effect": {
							"effect": "weakness",
							"target": "holder",
							"duration": 130,
							"amplifier": 1
						},
						"run_command": {
							"command": ["playsound scpdt.scp1025.read @a[r=10] ~~~"],
							"target": "holder"
						}
					},
					{
						"weight": 14,
						"add_mob_effect": {
							"effect": "slowness",
							"target": "holder",
							"duration": 140,
							"amplifier": 0
						},
						"run_command": {
							"command": ["playsound scpdt.scp1025.read @a[r=10] ~~~"],
							"target": "holder"
						}
					},
					{
						"weight": 10,
						"add_mob_effect": {
							"effect": "hunger",
							"target": "holder",
							"duration": 60,
							"amplifier": 1
						},
						"run_command": {
							"command": ["playsound scpdt.scp1025.read @a[r=10] ~~~"],
							"target": "holder"
						}
					},
					{
						"weight": 13,
						"add_mob_effect": {
							"effect": "mining_fatigue",
							"target": "holder",
							"duration": 120,
							"amplifier": 0
						},
						"run_command": {
							"command": ["playsound scpdt.scp1025.read @a[r=10] ~~~"],
							"target": "holder"
						}
					},
					{
						"weight": 3,
						"add_mob_effect": {
							"effect": "poison",
							"target": "holder",
							"duration": 43,
							"amplifier": 0
						},
						"run_command": {
							"command": ["playsound scpdt.scp1025.read @a[r=10] ~~~"],
							"target": "holder"
						}
					},
					{
						"weight": 2,
						"add_mob_effect": {
							"effect": "wither",
							"target": "holder",
							"duration": 16,
							"amplifier": 0
						},
						"run_command": {
							"command": ["playsound scpdt.scp1025.read @a[r=10] ~~~"],
							"target": "holder"
						}
					}
				]
			}
		}
	}
}
