{
	"format_version": "1.10.0",
	"minecraft:client_entity": {
		"description": {
			"identifier": "lc:dt_scp4959",
			"materials": {
				"default": "npc"
			},
			"textures": {
				"default": "textures/entity/dt_scp4959"
			},
			"geometry": {
				"default": "geometry.dt_scp4959"
			},
			"animations": {
				"general": "animation.dt_scp4959.general",
				"move": "animation.dt_scp4959.walking",

				"anim_cont": "controller.animation.dt_scp4959.anim_cont"
			},
			"scripts": {
				"animate": ["anim_cont"]
			},
			"render_controllers": ["controller.render.scp_dystopia"],
			"spawn_egg": {
				"base_color": "#CFCCC0",
				"overlay_color": "#AEA995"
			}
		}
	}
}
